cloudytab/__init__.py
cloudytab/cloudytab.py
cloudytab-0.1.0.dist-info/METADATA
cloudytab-0.1.0.dist-info/WHEEL
cloudytab-0.1.0.dist-info/licenses/LICENSE
cloudytab-0.1.0.dist-info/RECORD
